[
    {
        "title": "goblin",
        "id": 100,
        "cost": 1,
        "icon": "goblin.png",
        "card_back": "card_green.png",
        "type": "goblin"
    },
    {
        "title": "log",
        "id": 200,
        "cost": 1,
        "icon": "log.png",
        "card_back": "card_blue.png",
        "type": "resource"
    },
    {
        "title": "stick",
        "id": 201,
        "cost": 1,
        "icon": "log.png",
        "card_back": "card_blue.png",
        "type": "resource"
    },
    {
        "title": "fish",
        "id": 300,
        "cost": 1,
        "icon": "fish.png",
        "card_back": "card_yellow.png",
        "type": "food"
    },
    {
        "title": "pond",
        "id": 400,
        "cost": 1,
        "icon": "pond.png",
        "card_back": "card_red.png",
        "type": "structure"
    },
    {
        "title": "coin",
        "id": 500,
        "cost": 1,
        "icon": "coin.png",
        "card_back": "card_yellow.png",
        "type": "currency"
    }
]